sqltool/__init__.py
sqltool/mysql_client.py
sqltool/mysql_pool.py
sqltool/sql_gen.py
sqltool-0.1.13.dist-info/licenses/LICENSE
sqltool-0.1.13.dist-info/METADATA
sqltool-0.1.13.dist-info/WHEEL
sqltool-0.1.13.dist-info/top_level.txt
sqltool-0.1.13.dist-info/RECORD
