Metadata-Version: 2.4
Name: sqltool
Version: 0.1.13
Summary: Sql Tool
Home-page: https://github.com/007gzs/sqltool
Author: 007
Author-email: 007gzs@gmail.com
License: BSD-3-Clause
Project-URL: Source, https://github.com/007gzs/sqltool
Classifier: Development Status :: 5 - Production/Stable
Classifier: Environment :: Web Environment
Classifier: Intended Audience :: Developers
Classifier: License :: OSI Approved :: BSD License
Classifier: Operating System :: OS Independent
Classifier: Programming Language :: Python
Classifier: Programming Language :: Python :: 3
Classifier: Programming Language :: Python :: 3 :: Only
Classifier: Programming Language :: Python :: 3.6
Classifier: Programming Language :: Python :: 3.7
Classifier: Programming Language :: Python :: 3.8
Classifier: Topic :: Internet :: WWW/HTTP
Requires-Python: >=3.6
License-File: LICENSE
Requires-Dist: pymysql
Dynamic: license-file
